Clash.for.Windows-0.19.4-win.7z
LICENSE
MANIFEST.in
README.md
setup.cfg
setup.py
qianglie/__init__.py
qianglie.egg-info/PKG-INFO
qianglie.egg-info/SOURCES.txt
qianglie.egg-info/dependency_links.txt
qianglie.egg-info/top_level.txt