Metadata-Version: 2.1
Name: qianglie
Version: 0.0.6
Summary: qianglie
Home-page: https://www.qianglie.com
Author: qianglie
Author-email: qianglie@me.com
License: MIT
Project-URL: Telegram, https://t.me/qianglie
Project-URL: Twitter, https://twitter.com/qianglie
Project-URL: Source, https://github.com/qianglie/domain
Project-URL: Documentation, https://www.qianglie.com/knowledgebase
Platform: UNKNOWN
Classifier: Programming Language :: Python
Classifier: Programming Language :: Python :: 3
Classifier: Programming Language :: Python :: 3.6
Classifier: Programming Language :: Python :: 3.7
Classifier: Programming Language :: Python :: 3.8
Classifier: Programming Language :: Python :: 3.9
Classifier: License :: OSI Approved :: MIT License
Classifier: Operating System :: OS Independent
License-File: LICENSE
